easycrypto/__init__.py
easycrypto/crypto.py
easycrypto/key.py
easycrypto-1.1.4.dist-info/LICENSE
easycrypto-1.1.4.dist-info/METADATA
easycrypto-1.1.4.dist-info/WHEEL
easycrypto-1.1.4.dist-info/top_level.txt
easycrypto-1.1.4.dist-info/zip-safe
easycrypto-1.1.4.dist-info/RECORD
